qudit_sim/__init__.py
qudit_sim/config.py
qudit_sim/drive.py
qudit_sim/hamiltonian.py
qudit_sim/parallel.py
qudit_sim/pulse.py
qudit_sim/pulse_sim.py
qudit_sim/scale.py
qudit_sim/sim_result.py
qudit_sim/apps/__init__.py
qudit_sim/apps/find_heff.py
qudit_sim/apps/heff_tools.py
qudit_sim/apps/gates/__init__.py
qudit_sim/apps/gates/components.py
qudit_sim/apps/gates/pi_pulse.py
qudit_sim/visualization/__init__.py
qudit_sim/visualization/decompositions.py
qudit_sim/visualization/hamiltonian.py
qudit_sim/visualization/heff.py
qudit_sim-0.2.0.dist-info/LICENSE
qudit_sim-0.2.0.dist-info/METADATA
qudit_sim-0.2.0.dist-info/WHEEL
qudit_sim-0.2.0.dist-info/top_level.txt
qudit_sim-0.2.0.dist-info/RECORD
