Metadata-Version: 2.1
Name: qudit-sim
Version: 0.2.0
Summary: Multi-qudit system simulation and analysis
Home-page: https://github.com/UTokyo-ICEPP/qudit-sim
Author: Yutaro Iiyama
Author-email: iiyama@icepp.s.u-tokyo.ac.jp
Project-URL: Bug Tracker, https://github.com/UTokyo-ICEPP/qudit-sim/issues
Classifier: Programming Language :: Python :: 3
Classifier: License :: OSI Approved :: MIT License
Classifier: Operating System :: OS Independent
Requires-Python: >=3.6
License-File: LICENSE
Requires-Dist: numpy
Requires-Dist: qutip
Requires-Dist: h5py
Requires-Dist: jax
Requires-Dist: optax
Requires-Dist: scipy
Requires-Dist: matplotlib
Requires-Dist: rqutils (>=0.1.4)
